{
    "key": "group_5aaa6db083dc2",
    "title": "Footer",
    "fields": [
        {
            "key": "field_5aaa6ecd7758a",
            "label": "Footer Menu Links Column 1",
            "name": "footer_menu_links_column_1",
            "type": "repeater",
            "instructions": "",
            "required": 0,
            "conditional_logic": 0,
            "wrapper": {
                "width": "",
                "class": "",
                "id": ""
            },
            "collapsed": "field_5ae9ec65ea5ae",
            "min": 0,
            "max": 0,
            "layout": "table",
            "button_label": "Add Link",
            "sub_fields": [
                {
                    "key": "field_5ae9ec65ea5ae",
                    "label": "Link",
                    "name": "link",
                    "type": "link",
                    "instructions": "",
                    "required": 0,
                    "conditional_logic": 0,
                    "wrapper": {
                        "width": "",
                        "class": "",
                        "id": ""
                    },
                    "return_format": "array"
                }
            ]
        },
        {
            "key": "field_5ae9f30398533",
            "label": "Footer Menu Links Column 2",
            "name": "footer_menu_links_column_2",
            "type": "repeater",
            "instructions": "",
            "required": 0,
            "conditional_logic": 0,
            "wrapper": {
                "width": "",
                "class": "",
                "id": ""
            },
            "collapsed": "field_5ae9ec65ea5ae",
            "min": 0,
            "max": 0,
            "layout": "table",
            "button_label": "Add Link",
            "sub_fields": [
                {
                    "key": "field_5ae9f30398534",
                    "label": "Link",
                    "name": "link",
                    "type": "link",
                    "instructions": "",
                    "required": 0,
                    "conditional_logic": 0,
                    "wrapper": {
                        "width": "",
                        "class": "",
                        "id": ""
                    },
                    "return_format": "array"
                }
            ]
        },
        {
            "key": "field_5aaa8a02a509d",
            "label": "Footer Hours & Address",
            "name": "",
            "type": "message",
            "instructions": "",
            "required": 0,
            "conditional_logic": 0,
            "wrapper": {
                "width": "",
                "class": "",
                "id": ""
            },
            "message": "Hours, address, and admissions information can be managed in Pages>Visit.",
            "new_lines": "wpautop",
            "esc_html": 0
        }
    ],
    "location": [
        [
            {
                "param": "options_page",
                "operator": "==",
                "value": "acf-options-site-options-menus"
            }
        ]
    ],
    "menu_order": 3,
    "position": "normal",
    "style": "default",
    "label_placement": "left",
    "instruction_placement": "label",
    "hide_on_screen": "",
    "active": 1,
    "description": "(Site Options & Menus)",
    "modified": 1525281559
}